chatopt/__init__.py
chatopt/dataset/__init__.py
chatopt/dataset/reward_dataset.py
chatopt/dataset/utils.py
chatopt/experience_maker/__init__.py
chatopt/experience_maker/base.py
chatopt/experience_maker/naive.py
chatopt/nn/__init__.py
chatopt/nn/actor.py
chatopt/nn/bloom_actor.py
chatopt/nn/bloom_critic.py
chatopt/nn/bloom_rm.py
chatopt/nn/critic.py
chatopt/nn/generation.py
chatopt/nn/generation_utils.py
chatopt/nn/gpt_actor.py
chatopt/nn/gpt_critic.py
chatopt/nn/gpt_rm.py
chatopt/nn/lora.py
chatopt/nn/loss.py
chatopt/nn/opt_actor.py
chatopt/nn/opt_critic.py
chatopt/nn/opt_rm.py
chatopt/nn/reward_model.py
chatopt/nn/utils.py
chatopt/replay_buffer/__init__.py
chatopt/replay_buffer/base.py
chatopt/replay_buffer/naive.py
chatopt/replay_buffer/utils.py
chatopt/trainer/__init__.py
chatopt/trainer/base.py
chatopt/trainer/ppo.py
chatopt/trainer/rm.py
chatopt/trainer/utils.py
chatopt/trainer/callbacks/__init__.py
chatopt/trainer/callbacks/base.py
chatopt/trainer/callbacks/performance_evaluator.py
chatopt/trainer/strategies/__init__.py
chatopt/trainer/strategies/base.py
chatopt/trainer/strategies/colossalai.py
chatopt/trainer/strategies/ddp.py
chatopt/trainer/strategies/naive.py
minichatgpt/__init__.py
minichatgpt/dataset/__init__.py
minichatgpt/dataset/reward_dataset.py
minichatgpt/dataset/utils.py
minichatgpt/experience_maker/__init__.py
minichatgpt/experience_maker/base.py
minichatgpt/experience_maker/naive.py
minichatgpt/nn/__init__.py
minichatgpt/nn/actor.py
minichatgpt/nn/bloom_actor.py
minichatgpt/nn/bloom_critic.py
minichatgpt/nn/bloom_rm.py
minichatgpt/nn/critic.py
minichatgpt/nn/generation.py
minichatgpt/nn/generation_utils.py
minichatgpt/nn/gpt_actor.py
minichatgpt/nn/gpt_critic.py
minichatgpt/nn/gpt_rm.py
minichatgpt/nn/lora.py
minichatgpt/nn/loss.py
minichatgpt/nn/opt_actor.py
minichatgpt/nn/opt_critic.py
minichatgpt/nn/opt_rm.py
minichatgpt/nn/reward_model.py
minichatgpt/nn/utils.py
minichatgpt/replay_buffer/__init__.py
minichatgpt/replay_buffer/base.py
chatopt-0.0.1a0.dist-info/LICENSE
chatopt-0.0.1a0.dist-info/METADATA
chatopt-0.0.1a0.dist-info/WHEEL
chatopt-0.0.1a0.dist-info/top_level.txt
chatopt-0.0.1a0.dist-info/RECORD
